./.gitignore
./LICENSE
./PKG-INFO
./README.md
./README_CN.md
./config.py
./downloader.py
./install.ps1
./install.sh
./main.py
./pyproject.toml
./runner.py
./uv.lock
./.claude/settings.local.json
./.github/workflows/publish.yml
ifrp-1.0.0.dist-info/METADATA
ifrp-1.0.0.dist-info/WHEEL
ifrp-1.0.0.dist-info/entry_points.txt
ifrp-1.0.0.dist-info/licenses/LICENSE
ifrp-1.0.0.dist-info/RECORD
