Metadata-Version: 2.4
Name: ifrp
Version: 1.0.0
Summary: A TUI tool for managing frpc client
Project-URL: Homepage, https://github.com/lanbinleo/iFrp
Project-URL: Repository, https://github.com/lanbinleo/iFrp
Project-URL: Issues, https://github.com/lanbinleo/iFrp/issues
Author-email: ifrp <lanbinwolf@gmail.com>
License-Expression: MIT
License-File: LICENSE
Keywords: frp,frpc,nat,proxy,tui,tunnel
Classifier: Development Status :: 5 - Production/Stable
Classifier: Environment :: Console
Classifier: Intended Audience :: Developers
Classifier: Intended Audience :: System Administrators
Classifier: License :: OSI Approved :: MIT License
Classifier: Operating System :: OS Independent
Classifier: Programming Language :: Python :: 3
Classifier: Programming Language :: Python :: 3.10
Classifier: Programming Language :: Python :: 3.11
Classifier: Programming Language :: Python :: 3.12
Classifier: Topic :: System :: Networking
Classifier: Topic :: Utilities
Requires-Python: >=3.10
Requires-Dist: httpx>=0.25.0
Requires-Dist: questionary>=2.0.0
Requires-Dist: rich>=13.0.0
Requires-Dist: toml>=0.10.0
